app.py
autoVera.py
Module/formosa/generator.py
Module/formosa/mnemonic.py
Module/formosa/passwordGenerator.py
Module/formosa/passwordGeneratorLC.py
Module/formosa/tempPass.py
Module/formosa/themes/copy_left.json
Module/formosa/themes/finances.json
Module/formosa/themes/harry_potter.json
Module/formosa/themes/medieval_fantasy.json
Module/formosa/themes/sci-fi.json
Module/formosa/themes/the_big_bang_theory.json
Module/formosa/themes/tourism.json
Module/gui/rightclick.py
Module/keepass/keepass.py
Module/veracrypt/createContainer.py
Module/veracrypt/mountDrive.py
Module/veracrypt/writetest.py
headkuterWIN-1.0.dist-info/METADATA
headkuterWIN-1.0.dist-info/WHEEL
headkuterWIN-1.0.dist-info/entry_points.txt
headkuterWIN-1.0.dist-info/top_level.txt
headkuterWIN-1.0.dist-info/RECORD
