Metadata-Version: 2.1
Name: headkuterWIN
Version: 1.0
Summary: UNKNOWN
Home-page: UNKNOWN
Author: UNKNOWN
Author-email: UNKNOWN
License: UNKNOWN
Platform: UNKNOWN
Requires-Dist: click (==8.1.3)
Requires-Dist: colorama (==0.4.4)
